{"nodes": [{"id": "modelsv1_firebase_php", "label": "firebase.php", "file_type": "code", "source_file": "modelsv1\\firebase.php", "source_location": "L1"}, {"id": "firebase_firebasenotifier", "label": "FirebaseNotifier", "file_type": "code", "source_file": "modelsv1\\firebase.php", "source_location": "L3"}, {"id": "firebase_firebasenotifier_construct", "label": ".__construct()", "file_type": "code", "source_file": "modelsv1\\firebase.php", "source_location": "L7"}, {"id": "firebase_firebasenotifier_getaccesstoken", "label": ".getAccessToken()", "file_type": "code", "source_file": "modelsv1\\firebase.php", "source_location": "L12"}, {"id": "firebase_firebasenotifier_sendnotification", "label": ".sendNotification()", "file_type": "code", "source_file": "modelsv1\\firebase.php", "source_location": "L60"}], "edges": [{"source": "modelsv1_firebase_php", "target": "firebase_firebasenotifier", "relation": "contains", "confidence": "EXTRACTED", "source_file": "modelsv1\\firebase.php", "source_location": "L3", "weight": 1.0}, {"source": "firebase_firebasenotifier", "target": "firebase_firebasenotifier_construct", "relation": "method", "confidence": "EXTRACTED", "source_file": "modelsv1\\firebase.php", "source_location": "L7", "weight": 1.0}, {"source": "firebase_firebasenotifier", "target": "firebase_firebasenotifier_getaccesstoken", "relation": "method", "confidence": "EXTRACTED", "source_file": "modelsv1\\firebase.php", "source_location": "L12", "weight": 1.0}, {"source": "firebase_firebasenotifier", "target": "firebase_firebasenotifier_sendnotification", "relation": "method", "confidence": "EXTRACTED", "source_file": "modelsv1\\firebase.php", "source_location": "L60", "weight": 1.0}, {"source": "firebase_firebasenotifier_sendnotification", "target": "firebase_firebasenotifier_getaccesstoken", "relation": "calls", "confidence": "EXTRACTED", "source_file": "modelsv1\\firebase.php", "source_location": "L62", "weight": 1.0}], "raw_calls": [{"caller_nid": "firebase_firebasenotifier_getaccesstoken", "callee": "json_decode", "source_file": "modelsv1\\firebase.php", "source_location": "L14"}, {"caller_nid": "firebase_firebasenotifier_getaccesstoken", "callee": "file_get_contents", "source_file": "modelsv1\\firebase.php", "source_location": "L14"}, {"caller_nid": "firebase_firebasenotifier_getaccesstoken", "callee": "str_replace", "source_file": "modelsv1\\firebase.php", "source_location": "L18"}, {"caller_nid": "firebase_firebasenotifier_getaccesstoken", "callee": "json_encode", "source_file": "modelsv1\\firebase.php", "source_location": "L20"}, {"caller_nid": "firebase_firebasenotifier_getaccesstoken", "callee": "json_encode", "source_file": "modelsv1\\firebase.php", "source_location": "L21"}, {"caller_nid": "firebase_firebasenotifier_getaccesstoken", "callee": "time", "source_file": "modelsv1\\firebase.php", "source_location": "L25"}, {"caller_nid": "firebase_firebasenotifier_getaccesstoken", "callee": "time", "source_file": "modelsv1\\firebase.php", "source_location": "L26"}, {"caller_nid": "firebase_firebasenotifier_getaccesstoken", "callee": "base64_encode", "source_file": "modelsv1\\firebase.php", "source_location": "L29"}, {"caller_nid": "firebase_firebasenotifier_getaccesstoken", "callee": "base64_encode", "source_file": "modelsv1\\firebase.php", "source_location": "L30"}, {"caller_nid": "firebase_firebasenotifier_getaccesstoken", "callee": "openssl_sign", "source_file": "modelsv1\\firebase.php", "source_location": "L33"}, {"caller_nid": "firebase_firebasenotifier_getaccesstoken", "callee": "base64_encode", "source_file": "modelsv1\\firebase.php", "source_location": "L34"}, {"caller_nid": "firebase_firebasenotifier_getaccesstoken", "callee": "curl_init", "source_file": "modelsv1\\firebase.php", "source_location": "L43"}, {"caller_nid": "firebase_firebasenotifier_getaccesstoken", "callee": "curl_setopt", "source_file": "modelsv1\\firebase.php", "source_location": "L44"}, {"caller_nid": "firebase_firebasenotifier_getaccesstoken", "callee": "curl_setopt", "source_file": "modelsv1\\firebase.php", "source_location": "L45"}, {"caller_nid": "firebase_firebasenotifier_getaccesstoken", "callee": "curl_setopt", "source_file": "modelsv1\\firebase.php", "source_location": "L46"}, {"caller_nid": "firebase_firebasenotifier_getaccesstoken", "callee": "http_build_query", "source_file": "modelsv1\\firebase.php", "source_location": "L46"}, {"caller_nid": "firebase_firebasenotifier_getaccesstoken", "callee": "curl_setopt", "source_file": "modelsv1\\firebase.php", "source_location": "L47"}, {"caller_nid": "firebase_firebasenotifier_getaccesstoken", "callee": "curl_exec", "source_file": "modelsv1\\firebase.php", "source_location": "L49"}, {"caller_nid": "firebase_firebasenotifier_getaccesstoken", "callee": "curl_close", "source_file": "modelsv1\\firebase.php", "source_location": "L50"}, {"caller_nid": "firebase_firebasenotifier_getaccesstoken", "callee": "json_decode", "source_file": "modelsv1\\firebase.php", "source_location": "L52"}, {"caller_nid": "firebase_firebasenotifier_getaccesstoken", "callee": "isset", "source_file": "modelsv1\\firebase.php", "source_location": "L53"}, {"caller_nid": "firebase_firebasenotifier_getaccesstoken", "callee": "json_encode", "source_file": "modelsv1\\firebase.php", "source_location": "L56"}, {"caller_nid": "firebase_firebasenotifier_sendnotification", "callee": "curl_init", "source_file": "modelsv1\\firebase.php", "source_location": "L80"}, {"caller_nid": "firebase_firebasenotifier_sendnotification", "callee": "curl_setopt", "source_file": "modelsv1\\firebase.php", "source_location": "L81"}, {"caller_nid": "firebase_firebasenotifier_sendnotification", "callee": "curl_setopt", "source_file": "modelsv1\\firebase.php", "source_location": "L82"}, {"caller_nid": "firebase_firebasenotifier_sendnotification", "callee": "curl_setopt", "source_file": "modelsv1\\firebase.php", "source_location": "L83"}, {"caller_nid": "firebase_firebasenotifier_sendnotification", "callee": "curl_setopt", "source_file": "modelsv1\\firebase.php", "source_location": "L84"}, {"caller_nid": "firebase_firebasenotifier_sendnotification", "callee": "curl_setopt", "source_file": "modelsv1\\firebase.php", "source_location": "L85"}, {"caller_nid": "firebase_firebasenotifier_sendnotification", "callee": "json_encode", "source_file": "modelsv1\\firebase.php", "source_location": "L85"}, {"caller_nid": "firebase_firebasenotifier_sendnotification", "callee": "curl_exec", "source_file": "modelsv1\\firebase.php", "source_location": "L87"}, {"caller_nid": "firebase_firebasenotifier_sendnotification", "callee": "curl_error", "source_file": "modelsv1\\firebase.php", "source_location": "L89"}, {"caller_nid": "firebase_firebasenotifier_sendnotification", "callee": "curl_close", "source_file": "modelsv1\\firebase.php", "source_location": "L92"}, {"caller_nid": "firebase_firebasenotifier_sendnotification", "callee": "json_decode", "source_file": "modelsv1\\firebase.php", "source_location": "L93"}]}